llama/.env
llama/__init__.py
llama/settings.py
llama/starter.py
smallest_llama-0.0.1.dist-info/METADATA
smallest_llama-0.0.1.dist-info/WHEEL
smallest_llama-0.0.1.dist-info/top_level.txt
smallest_llama-0.0.1.dist-info/RECORD
